execelasticsearch/__init__.py
execelasticsearch/connection.py
execelasticsearch/handler.py
execelasticsearch/mapping.py
exec_es-0.0.11.dist-info/LICENSE
exec_es-0.0.11.dist-info/METADATA
exec_es-0.0.11.dist-info/WHEEL
exec_es-0.0.11.dist-info/top_level.txt
exec_es-0.0.11.dist-info/RECORD
