Metadata-Version: 2.1
Name: exec-es
Version: 0.0.11
Summary: ElasticSearch Handler
Home-page: https://github.com/Supplayer/exec_es.git
Author: Supplayer
Author-email: x254724521@hotmail.com
License: UNKNOWN
Platform: UNKNOWN
Classifier: Programming Language :: Python :: 3
Classifier: License :: OSI Approved :: MIT License
Classifier: Operating System :: OS Independent
Requires-Python: >=3.6
License-File: LICENSE
Requires-Dist: elasticsearch
Requires-Dist: requests
